microbot/__init__.py
pymicrobot-0.0.23.dist-info/licenses/LICENSE
pymicrobot-0.0.23.dist-info/METADATA
pymicrobot-0.0.23.dist-info/WHEEL
pymicrobot-0.0.23.dist-info/top_level.txt
pymicrobot-0.0.23.dist-info/RECORD
